simtool/__init__.py
simtool/cachedrun.py
simtool/datastore.py
simtool/db.py
simtool/encode.py
simtool/experiment.py
simtool/mpimagic.py
simtool/params.py
simtool/run.py
simtool/utils.py
simtool-0.4.4.dist-info/AUTHORS.rst
simtool-0.4.4.dist-info/LICENSE
simtool-0.4.4.dist-info/METADATA
simtool-0.4.4.dist-info/WHEEL
simtool-0.4.4.dist-info/top_level.txt
simtool-0.4.4.dist-info/RECORD
