Metadata-Version: 2.1
Name: simtool
Version: 0.4.4
Summary: Functions for creating and running sim2Ls
Home-page: https://github.com/hubzero/simtool
Maintainer: Steven Clark
Maintainer-email: smclark@sdsc.edu
License: MIT license
Keywords: simtool
Platform: UNKNOWN
Classifier: Development Status :: 2 - Pre-Alpha
Classifier: Intended Audience :: Developers
Classifier: License :: OSI Approved :: MIT License
Classifier: Natural Language :: English
Classifier: Programming Language :: Python :: 3
Classifier: Programming Language :: Python :: 3.4
Classifier: Programming Language :: Python :: 3.5
Classifier: Programming Language :: Python :: 3.6
Classifier: Programming Language :: Python :: 3.7
Classifier: Programming Language :: Python :: 3.8
Requires-Dist: ipython
Requires-Dist: joblib
Requires-Dist: jsonpickle
Requires-Dist: mendeleev
Requires-Dist: numpy
Requires-Dist: papermill
Requires-Dist: pillow
Requires-Dist: pint
Requires-Dist: scrapbook
